AUTHORS.txt
CHANGELOG.txt
LICENSE.txt
MANIFEST.in
README.txt
setup.cfg
setup.py
Blogmaker.egg-info/PKG-INFO
Blogmaker.egg-info/SOURCES.txt
Blogmaker.egg-info/dependency_links.txt
Blogmaker.egg-info/requires.txt
Blogmaker.egg-info/top_level.txt
blogmaker/__init__.py
blogmaker/blog/__init__.py
blogmaker/blog/admin_urls.py
blogmaker/blog/admin_views.py
blogmaker/blog/feeds.py
blogmaker/blog/models.py
blogmaker/blog/tests.py
blogmaker/blog/trackback_client.py
blogmaker/blog/trackback_client_test.py
blogmaker/blog/trackback_update.py
blogmaker/blog/trackback_update_test.py
blogmaker/blog/trackback_views.py
blogmaker/blog/urls.py
blogmaker/blog/urls_tools.py
blogmaker/blog/media/css/blogmaker_tools.css
blogmaker/blog/media/js/entry_change_form.js
blogmaker/blog/media/js/jquery.js
blogmaker/blog/media/release/.DS_Store
blogmaker/blog/media/release/.htaccess
blogmaker/blog/media/release/README.html
blogmaker/blog/migrations/__init__.py
blogmaker/blog/migrations/migrator.py
blogmaker/blog/migrations/sql/AddTrackbackStatus.sql
blogmaker/blog/migrations/sql/AddTrackbackUrl.sql
blogmaker/blog/migrations/sql/ConsolidatePubDate.sql
blogmaker/blog/migrations/sql/LongerEntrySlug.sql
blogmaker/blog/migrations/sql/LongerTrackbackStatusLink.sql
blogmaker/blog/migrations/sql/MakeBlogPackage.sql
blogmaker/blog/migrations/sql/MoreBlogPackage.sql
blogmaker/blog/migrations/sql/TrackbackMessageIsText.sql
blogmaker/blog/migrations/sql/init.sql
blogmaker/blog/templates/blog/blog_base.html
blogmaker/blog/templates/blog/entry_archive.html
blogmaker/blog/templates/blog/entry_archive_day.html
blogmaker/blog/templates/blog/entry_archive_month.html
blogmaker/blog/templates/blog/entry_archive_year.html
blogmaker/blog/templates/blog/entry_detail.html
blogmaker/blog/templates/blog/post_trackback_form.html
blogmaker/blog/templates/blog/search.html
blogmaker/blog/templates/blog/search_results.html
blogmaker/blog/templates/blog/tag_index.html
blogmaker/blog/templates/blog/tag_list.html
blogmaker/blog/templates/blog/user_index.html
blogmaker/blog/templates/blog/includes/blog_nav.html
blogmaker/blog/templates/blog/includes/blog_search.html
