Metadata-Version: 1.0
Name: Blogmaker
Version: 0.6
Summary: Blog application for Django
Home-page: http://code.google.com/p/blogmaker/
Author: Peter Bernheim, Kent S Johnson
Author-email: blogmaker@blogcosm.com
License: BSD License
Keywords: django,blog
Platform: any
Classifier: Development Status :: 5 - Production/Stable
Classifier: Environment :: Web Environment
Classifier: Intended Audience :: Developers
Classifier: License :: OSI Approved :: BSD License
Classifier: Natural Language :: English
Classifier: Operating System :: OS Independent
Classifier: Programming Language :: Python
Classifier: Topic :: Internet :: WWW/HTTP :: Dynamic Content
